<english>
 <b id="0">Bullet Diameter: </b>
 <b id="1">Neck Diameter: </b>
 <b id="2">Shoulder Diameter: </b>
 <b id="3">Base Diameter: </b>
 <b id="4">Rim Diameter: </b>
 <b id="5">Rim Thickness: </b>
 <b id="6">Case Length: </b>
 <b id="7">Overall Length: </b>
 <b id="8">Case Capacity: </b>
 <b id="9">Primer Small Pistol</b>
 <b id="10">Primer Large Pistol</b>
 <b id="11">Primer Small Rifle</b>
 <b id="12">Primer Large Rifle</b>
 <b id="13">Rimfire</b>
 <b id="14">Primer 8mm</b>
 <b id="15">Shotshell Primer</b>
</english>
